{
  "project_info": {
    "project_number": "600698365943",
    "project_id": "icsa-microservices",
    "storage_bucket": "icsa-microservices.firebasestorage.app"
  },
  "client": [
    {
      "client_info": {
        "mobilesdk_app_id": "1:600698365943:android:939fd7bbc7deac611e30f2",
        "android_client_info": {
          "package_name": "com.example.icsa_mobile_app"
        }
      },
      "oauth_client": [],
      "api_key": [
        {
          "current_key": "AIzaSyDPbWpX5Zz_SB5YJkrDAYycuzvlGYDLopA"
        }
      ],
      "services": {
        "appinvite_service": {
          "other_platform_oauth_client": []
        }
      }
    }
  ],
  "configuration_version": "1"
}